kpireport_static/__init__.py
kpireport_static/output.py
kpireport_static-0.1.1.dist-info/METADATA
kpireport_static-0.1.1.dist-info/WHEEL
kpireport_static-0.1.1.dist-info/entry_points.txt
kpireport_static-0.1.1.dist-info/top_level.txt
kpireport_static-0.1.1.dist-info/RECORD
